pzflow/__init__.py
pzflow/bijectors.py
pzflow/distributions.py
pzflow/example_files/checkerboard-data.pkl
pzflow/example_files/city-data.pkl
pzflow/example_files/example-flow.pzflow.pkl
pzflow/example_files/galaxy-data.pkl
pzflow/example_files/two-moons-data.pkl
pzflow/examples.py
pzflow/flow.py
pzflow/flowEnsemble.py
pzflow/utils.py
pzflow-3.3.0.dist-info/LICENSE
pzflow-3.3.0.dist-info/METADATA
pzflow-3.3.0.dist-info/WHEEL
pzflow-3.3.0.dist-info/RECORD
