Metadata-Version: 2.3
Name: pzflow
Version: 3.3.0
Summary: Probabilistic modeling of tabular data with normalizing flows.
License: MIT
Author: John Franklin Crenshaw
Author-email: jfcrenshaw@gmail.com
Requires-Python: >=3.10,<4.0
Classifier: License :: OSI Approved :: MIT License
Classifier: Programming Language :: Python :: 3
Classifier: Programming Language :: Python :: 3.10
Classifier: Programming Language :: Python :: 3.11
Classifier: Programming Language :: Python :: 3.12
Classifier: Programming Language :: Python :: 3.13
Requires-Dist: jax (>=0.5.3)
Requires-Dist: jaxlib (>=0.5.3)
Requires-Dist: optax (>=0.2.4)
Requires-Dist: pandas (>=2.2.3)
Requires-Dist: tqdm (>=4.67.1)
Project-URL: Repository, https://github.com/jfcrenshaw/pzflow
